{"url":"https://uptane.github.io//docs/2.0.0/enhancements/pures/pure1","viewport":{"width":1280,"height":720},"colorScheme":"light","mediaType":"screen","test":{"id":"036fbb4866a3417c3424-3f16719312bf155050f5","title":"pathname /docs/2.0.0/enhancements/pures/pure1","titlePath":["argos/screenshot.spec.js","Docusaurus site screenshots","pathname /docs/2.0.0/enhancements/pures/pure1"],"location":{"file":"argos/screenshot.spec.js","line":20,"column":9}},"browser":{"name":"chromium","version":"119.0.6045.9"},"automationLibrary":{"version":"1.39.0","name":"@playwright/test"},"sdk":{"name":"@argos-ci/playwright","version":"1.0.1"}}